Metadata-Version: 2.1
Name: check-docstring
Version: 1.0.1
Summary: BD RD docstring format checker.
Home-page: UNKNOWN
License: UNKNOWN
Platform: UNKNOWN
Requires-Python: >=3.6.*
Provides-Extra: dev
